katti/__init__.py
katti/configloader.py
katti/constants.py
katti/localproblems.py
katti/main.py
katti/parser.py
katti/problem_ids.json
katti/selected_ids.json
katti/unsolved_problems.json
katti/user_config.json
katti/utils.py
katti/webkattis.py
katti-0.0.3.dist-info/LICENSE
katti-0.0.3.dist-info/METADATA
katti-0.0.3.dist-info/WHEEL
katti-0.0.3.dist-info/entry_points.txt
katti-0.0.3.dist-info/top_level.txt
katti-0.0.3.dist-info/RECORD
