Metadata-Version: 2.1
Name: katti
Version: 0.0.3
Summary: Commandline tool for Kattis problems
Author-email: Matthew Freestone <matthewfreestone1593@gmail.com>
License: MIT License
Project-URL: Homepage, https://github.com/MatthewFreestone/katti
Keywords: kattis
Requires-Python: >3.7
License-File: LICENSE
Requires-Dist: requests >=2
Requires-Dist: beautifulsoup4 >=4
Requires-Dist: setuptools >=69
